MANIFEST.in
README.md
setup.cfg
setup.py
ecco_cloud_utils/__init__.py
ecco_cloud_utils/date_time.py
ecco_cloud_utils/geometry.py
ecco_cloud_utils/llc_array_conversion.py
ecco_cloud_utils/mapping.py
ecco_cloud_utils/records.py
ecco_cloud_utils.egg-info/PKG-INFO
ecco_cloud_utils.egg-info/SOURCES.txt
ecco_cloud_utils.egg-info/dependency_links.txt
ecco_cloud_utils.egg-info/requires.txt
ecco_cloud_utils.egg-info/top_level.txt